mailbridge/__init__.py
mailbridge/client.py
mailbridge/exceptions.py
mailbridge/dto/__init__.py
mailbridge/dto/bulk_email_dto.py
mailbridge/dto/bulk_email_response_dto.py
mailbridge/dto/email_message_dto.py
mailbridge/dto/email_response_dto.py
mailbridge/providers/__init__.py
mailbridge/providers/base_email_provider.py
mailbridge/providers/brevo_provider.py
mailbridge/providers/mailgun_provider.py
mailbridge/providers/postmark_provider.py
mailbridge/providers/sendgrid_provider.py
mailbridge/providers/ses_provider.py
mailbridge/providers/smtp_provider.py
mailbridge-2.0.0.dist-info/licenses/LICENSE
mailbridge-2.0.0.dist-info/METADATA
mailbridge-2.0.0.dist-info/WHEEL
mailbridge-2.0.0.dist-info/top_level.txt
mailbridge-2.0.0.dist-info/RECORD
