Metadata-Version: 2.4
Name: mailbridge
Version: 2.0.0
Summary: Unified Python email library with multi-provider support (SendGrid, SES, Postmark, Mailgun, Brevo, SMTP)
Author-email: Radomir Brkovic <brkovic.radomir@gmail.com>
Maintainer-email: Radomir Brkovic <brkovic.radomir@gmail.com>
License: MIT
Project-URL: Homepage, https://github.com/radomirbrkovic/mailbridge
Project-URL: Documentation, https://github.com/radomirbrkovic/mailbridge#readme
Project-URL: Repository, https://github.com/radomirbrkovic/mailbridge
Project-URL: Issues, https://github.com/radomirbrkovic/mailbridge/issues
Project-URL: Changelog, https://github.com/radomirbrkovic/mailbridge/blob/main/CHANGELOG.md
Keywords: email,sendgrid,ses,postmark,mailgun,brevo,smtp,mail,email-sending,transactional-email,bulk-email,template-email
Classifier: Development Status :: 5 - Production/Stable
Classifier: Intended Audience :: Developers
Classifier: License :: OSI Approved :: MIT License
Classifier: Operating System :: OS Independent
Classifier: Programming Language :: Python :: 3
Classifier: Programming Language :: Python :: 3.8
Classifier: Programming Language :: Python :: 3.9
Classifier: Programming Language :: Python :: 3.10
Classifier: Programming Language :: Python :: 3.11
Classifier: Programming Language :: Python :: 3.12
Classifier: Topic :: Communications :: Email
Classifier: Topic :: Software Development :: Libraries :: Python Modules
Classifier: Typing :: Typed
Requires-Python: >=3.8
License-File: LICENSE
Requires-Dist: requests>=2.28.0
Requires-Dist: pydantic>=2.0.0
Provides-Extra: sendgrid
Requires-Dist: sendgrid>=6.10.0; extra == "sendgrid"
Provides-Extra: ses
Requires-Dist: boto3>=1.28.0; extra == "ses"
Provides-Extra: mailgun
Requires-Dist: requests>=2.28.0; extra == "mailgun"
Provides-Extra: postmark
Requires-Dist: requests>=2.28.0; extra == "postmark"
Provides-Extra: brevo
Requires-Dist: requests>=2.28.0; extra == "brevo"
Provides-Extra: all
Requires-Dist: sendgrid>=6.10.0; extra == "all"
Requires-Dist: boto3>=1.28.0; extra == "all"
Provides-Extra: dev
Requires-Dist: pytest>=7.4.0; extra == "dev"
Requires-Dist: pytest-cov>=4.1.0; extra == "dev"
Requires-Dist: pytest-mock>=3.11.1; extra == "dev"
Requires-Dist: black>=23.7.0; extra == "dev"
Requires-Dist: flake8>=6.1.0; extra == "dev"
Requires-Dist: mypy>=1.5.0; extra == "dev"
Requires-Dist: isort>=5.12.0; extra == "dev"
Requires-Dist: pre-commit>=3.3.3; extra == "dev"
Provides-Extra: docs
Requires-Dist: sphinx>=7.0.0; extra == "docs"
Requires-Dist: sphinx-rtd-theme>=1.3.0; extra == "docs"
Requires-Dist: sphinx-autodoc-typehints>=1.24.0; extra == "docs"
Dynamic: license-file
